PLApp/__init__.py
PLApp/main.py
PLApp/Layout/__init__.py
PLApp/Layout/frames_buttons.py
PLApp/Layout/layouts_style.py
PLApp/Layout/main_window_att.py
PLApp/Layout/setting_windows.py
PLApp/Plot/__init__.py
PLApp/Plot/frame_attributes.py
PLApp/Plot/plot_functions.py
PLApp/Plot/plot_style.py
PLApp/Plot/utils.py
PLApp/Processing/__init__.py
PLApp/Processing/function_common.py
PLApp/Processing/photoluminescencegan.py
PLApp/Processing/sequences.py
plalgan-1.0.1.dist-info/licenses/LICENSE
plalgan-1.0.1.dist-info/METADATA
plalgan-1.0.1.dist-info/WHEEL
plalgan-1.0.1.dist-info/entry_points.txt
plalgan-1.0.1.dist-info/top_level.txt
plalgan-1.0.1.dist-info/RECORD
